{
  "required": true,
  "package": "com.iafenvoy.origins.mixin",
  "compatibilityLevel": "JAVA_21",
  "mixins": [
    "accessor.LivingEntityAccessor",
    "accessor.MobAccessor",
    "power.BlockStateBaseMixin",
    "power.CommonHooksMixin",
    "power.ConduitPowerOnLandMixin",
    "power.FoodDataMixin",
    "power.LivingEntityMixin",
    "power.PlayerMixin",
    "power.ScareCreepersMixin",
    "power.SelectionInvulnerabilityMixin",
    "power.WaterBreathingMixin$BreathingImpl",
    "power.WaterBreathingMixin$TurtleHelmetProxy"
  ],
  "client": [
    "power.EntityMixin",
    "power.EntityRenderDispatcherMixin",
    "power.FogRendererMixin",
    "power.GameRendererMixin",
    "power.PlayerRendererMixin",
    "power.WaterVisionMixin"
  ],
  "injectors": {
    "defaultRequire": 1
  },
  "overwrites": {
    "requireAnnotations": true
  }
}